json_extract.py
python_json_extract-0.1.1.dist-info/LICENSE
python_json_extract-0.1.1.dist-info/WHEEL
python_json_extract-0.1.1.dist-info/METADATA
python_json_extract-0.1.1.dist-info/RECORD
