Metadata-Version: 2.3
Name: python-json-extract
Version: 0.1.1
Summary: Simple library to extract value from json.
Classifier: License :: OSI Approved :: MIT License
